pinepy/__init__.py
pinepy/brokers/__init__.py
pinepy/brokers/_broker.py
pinepy/engine/__init__.py
pinepy/engine/_engine.py
pinepy/engine/_models.py
pinepy/ti/__init__.py
pinepy/ti/_behavior.py
pinepy/ti/_examples.py
pinepy/ti/_models.py
pinepy-0.1.12.dist-info/METADATA
pinepy-0.1.12.dist-info/WHEEL
pinepy-0.1.12.dist-info/top_level.txt
pinepy-0.1.12.dist-info/RECORD
