Metadata-Version: 2.4
Name: pinepy
Version: 0.1.12
Summary: Add your description here
Requires-Python: >=3.12
Requires-Dist: polars>=1.29.0
Requires-Dist: talipp>=2.5.0
